Metadata-Version: 2.4
Name: adafruit-circuitpython-max1704x
Version: 1.0.14
Summary: MAX17048 or MAX17049 battery fuel gauge Python/CircuitPython library
Author-email: Adafruit Industries <circuitpython@adafruit.com>
License: MIT
Project-URL: Homepage, https://github.com/adafruit/Adafruit_CircuitPython_MAX1704x.git
Keywords: adafruit,blinka,circuitpython,micropython,max1704x,max17048,max17049,battery,lipoly,lipo,fuel,gauge,monitor
Classifier: Intended Audience :: Developers
Classifier: Topic :: Software Development :: Libraries
Classifier: Topic :: Software Development :: Embedded Systems
Classifier: Topic :: System :: Hardware
Classifier: License :: OSI Approved :: MIT License
Classifier: Programming Language :: Python :: 3
License-File: LICENSE
Requires-Dist: Adafruit-Blinka
Requires-Dist: adafruit-circuitpython-busdevice
Requires-Dist: adafruit-circuitpython-register
Provides-Extra: optional
Dynamic: license-file
